folklore_cli/__init__.py
folklore_cli/runner.py
folklore_cli/cmds/__init__.py
folklore_cli/cmds/_base.py
folklore_cli/cmds/deploy.py
folklore_cli/cmds/help.py
folklore_cli/cmds/serve.py
folklore_cli/cmds/shell.py
folklore_cli/deploy/__init__.py
folklore_cli/deploy/playbook/crontab.yml
folklore_cli/deploy/playbook/deploy.yml
folklore_cli/deploy/playbook/playbook.yml
folklore_cli/deploy/playbook/files/logrotate.j2
folklore_cli/deploy/playbook/files/rsyslog.j2
folklore_cli/deploy/playbook/files/supervisor.j2
folklore_cli-0.2.0.dist-info/LICENSE
folklore_cli-0.2.0.dist-info/METADATA
folklore_cli-0.2.0.dist-info/WHEEL
folklore_cli-0.2.0.dist-info/entry_points.txt
folklore_cli-0.2.0.dist-info/top_level.txt
folklore_cli-0.2.0.dist-info/RECORD
