Metadata-Version: 2.1
Name: folklore-cli
Version: 0.2.0
Summary: Folklore service framework command line toolkit
Home-page: https://github.com/maralla/folklore-cli
Author: maralla
Author-email: imaralla@icloud.com
License: UNKNOWN
Platform: UNKNOWN
Requires-Dist: folklore
Requires-Dist: folklore-ext
Requires-Dist: folklore-config
Requires-Dist: docopt
Requires-Dist: schema
Requires-Dist: gevent (>=1.2.1)
Requires-Dist: thriftpy
Requires-Dist: gunicorn
Provides-Extra: deploy
Requires-Dist: ansible (>=2.2.0.0) ; extra == 'deploy'
Provides-Extra: shell
Requires-Dist: folklore-client ; extra == 'shell'
Requires-Dist: IPython ; extra == 'shell'
